dns_aid/__init__.py
dns_aid/py.typed
dns_aid/backends/__init__.py
dns_aid/backends/base.py
dns_aid/backends/ddns.py
dns_aid/backends/mock.py
dns_aid/backends/route53.py
dns_aid/backends/infoblox/__init__.py
dns_aid/backends/infoblox/bloxone.py
dns_aid/backends/infoblox/nios.py
dns_aid/cli/__init__.py
dns_aid/cli/main.py
dns_aid/core/__init__.py
dns_aid/core/discoverer.py
dns_aid/core/models.py
dns_aid/core/publisher.py
dns_aid/core/validator.py
dns_aid/mcp/__init__.py
dns_aid/mcp/server.py
dns_aid/utils/__init__.py
dns_aid/utils/logging.py
dns_aid/utils/validation.py
dns_aid-0.2.0.dist-info/METADATA
dns_aid-0.2.0.dist-info/WHEEL
dns_aid-0.2.0.dist-info/entry_points.txt
dns_aid-0.2.0.dist-info/licenses/LICENSE
dns_aid-0.2.0.dist-info/RECORD
