Metadata-Version: 2.4
Name: dns-aid
Version: 0.2.0
Summary: DNS-based Agent Identification and Discovery - Reference Implementation
Project-URL: Homepage, https://github.com/iracic82/dns-aid
Project-URL: Documentation, https://github.com/iracic82/dns-aid#readme
Project-URL: Repository, https://github.com/iracic82/dns-aid
Author: DNS-AID Contributors
License-Expression: Apache-2.0
License-File: LICENSE
Keywords: a2a,agent,ai,discovery,dns,dnssec,mcp,svcb
Classifier: Development Status :: 3 - Alpha
Classifier: Intended Audience :: Developers
Classifier: License :: OSI Approved :: Apache Software License
Classifier: Programming Language :: Python :: 3
Classifier: Programming Language :: Python :: 3.11
Classifier: Programming Language :: Python :: 3.12
Classifier: Topic :: Internet :: Name Service (DNS)
Classifier: Topic :: Scientific/Engineering :: Artificial Intelligence
Requires-Python: >=3.11
Requires-Dist: dnspython>=2.6.0
Requires-Dist: httpx>=0.27.0
Requires-Dist: pydantic>=2.5.0
Requires-Dist: structlog>=24.0.0
Provides-Extra: all
Requires-Dist: boto3-stubs[route53]>=1.34.0; extra == 'all'
Requires-Dist: boto3>=1.34.0; extra == 'all'
Requires-Dist: mcp>=1.0.0; extra == 'all'
Requires-Dist: mypy>=1.8.0; extra == 'all'
Requires-Dist: pytest-asyncio>=0.23.0; extra == 'all'
Requires-Dist: pytest-cov>=4.0.0; extra == 'all'
Requires-Dist: pytest>=8.0.0; extra == 'all'
Requires-Dist: rich>=13.0.0; extra == 'all'
Requires-Dist: ruff>=0.3.0; extra == 'all'
Requires-Dist: typer>=0.12.0; extra == 'all'
Requires-Dist: uvicorn>=0.30.0; extra == 'all'
Provides-Extra: cli
Requires-Dist: rich>=13.0.0; extra == 'cli'
Requires-Dist: typer>=0.12.0; extra == 'cli'
Provides-Extra: dev
Requires-Dist: boto3-stubs[route53]>=1.34.0; extra == 'dev'
Requires-Dist: mypy>=1.8.0; extra == 'dev'
Requires-Dist: pytest-asyncio>=0.23.0; extra == 'dev'
Requires-Dist: pytest-cov>=4.0.0; extra == 'dev'
Requires-Dist: pytest>=8.0.0; extra == 'dev'
Requires-Dist: ruff>=0.3.0; extra == 'dev'
Provides-Extra: infoblox
Provides-Extra: mcp
Requires-Dist: mcp>=1.0.0; extra == 'mcp'
Requires-Dist: uvicorn>=0.30.0; extra == 'mcp'
Provides-Extra: route53
Requires-Dist: boto3>=1.34.0; extra == 'route53'
